roler
