Metadata-Version: 1.1
Name: roler
Version: 0.2
Summary: A simple tool that creates an ansible role                  with the reccomended directory layout
Home-page: https://github.com/TheDivic/roler
Author: Nikola Divic
Author-email: divicnikola@gmail.com
License: UNKNOWN
Download-URL: https://github.com/TheDivic/roler/tarball/0.2
Keywords: ansible,role
Platform: UNKNOWN
